gpx_trip/__init__.py
gpx_trip-0.0.2.dev0.data/scripts/gpx_trip
gpx_trip-0.0.2.dev0.dist-info/LICENCE.txt
gpx_trip-0.0.2.dev0.dist-info/METADATA
gpx_trip-0.0.2.dev0.dist-info/WHEEL
gpx_trip-0.0.2.dev0.dist-info/top_level.txt
gpx_trip-0.0.2.dev0.dist-info/RECORD
